moosee/__init__.py
moosee/__main__.py
moosee/config.py
moosee-0.1.0.dist-info/entry_points.txt
moosee-0.1.0.dist-info/WHEEL
moosee-0.1.0.dist-info/METADATA
moosee-0.1.0.dist-info/RECORD
