Metadata-Version: 2.1
Name: moosee
Version: 0.1.0
Summary: 
Home-page: https://github.com/wvlab/moosee
License: GPL-3.0-or-later
Author: wvlab
Author-email: wvlab@protonmail.com
Maintainer: wvlab
Maintainer-email: wvlab@protonmail.com
Requires-Python: >=3.6,<4.0
Classifier: License :: OSI Approved :: GNU General Public License v3 or later (GPLv3+)
Classifier: Programming Language :: Python :: 3
Classifier: Programming Language :: Python :: 3.10
Classifier: Programming Language :: Python :: 3.6
Classifier: Programming Language :: Python :: 3.7
Classifier: Programming Language :: Python :: 3.8
Classifier: Programming Language :: Python :: 3.9
Classifier: Topic :: Development Status :: 1 - Planning
Requires-Dist: keyboard (>=0.13.5,<0.14.0)
Requires-Dist: mss (>=6.1.0,<7.0.0)
Requires-Dist: opencv-python (>=4.6.0,<5.0.0)
Requires-Dist: pynput (>=1.7.6,<2.0.0)
Project-URL: Repository, https://github.com/wvlab/moosee
